cmusic/__init__.py
cmusic/bg_threads.py
cmusic/cmusic.py
cmusic/constants.py
cmusic/indexlib.py
cmusic/main.py
cmusic-1.2.0.dist-info/LICENSE
cmusic-1.2.0.dist-info/METADATA
cmusic-1.2.0.dist-info/WHEEL
cmusic-1.2.0.dist-info/entry_points.txt
cmusic-1.2.0.dist-info/RECORD
