Metadata-Version: 2.1
Name: cmusic
Version: 1.2.0
Summary: the CLI music player
Author: Kokonico
Author-email: kokonico@duck.com
Requires-Python: >=3.12,<4.0
Classifier: Programming Language :: Python :: 3
Classifier: Programming Language :: Python :: 3.12
Requires-Dist: inquirer (>=3.2.4,<4.0.0)
Requires-Dist: mutagen (>=1.47.0,<2.0.0)
Requires-Dist: objlog (>=2.1.5,<3.0.0)
Requires-Dist: pygame (>=2.5.2,<3.0.0)
Requires-Dist: tinytag (>=1.10.1,<2.0.0)
